gpt_playground/chain.py
gpt_playground/prompts.py
gpt_playground/shell.py
gpt_playground/society.py
gptme/__init__.py
gptme/cache.py
gptme/cli.py
gptme/constants.py
gptme/logmanager.py
gptme/message.py
gptme/prompts.py
gptme/py.typed
gptme/reduce.py
gptme/tools/__init__.py
gptme/util.py
gpt_playground-0.1.1.dist-info/METADATA
gpt_playground-0.1.1.dist-info/WHEEL
gpt_playground-0.1.1.dist-info/entry_points.txt
gpt_playground-0.1.1.dist-info/RECORD
