Metadata-Version: 2.1
Name: gpt-playground
Version: 0.1.1
Summary: 
Author: Erik Bjäreholt
Author-email: erik@bjareho.lt
Requires-Python: >=3.10,<4.0
Classifier: Programming Language :: Python :: 3
Classifier: Programming Language :: Python :: 3.10
Classifier: Programming Language :: Python :: 3.11
Requires-Dist: beautifulsoup4 (>=4.12.0,<5.0.0)
Requires-Dist: chromadb (>=0.3,<0.4)
Requires-Dist: click (>=8.0,<9.0)
Requires-Dist: colorama (>=0.4.6,<0.5.0)
Requires-Dist: google-search-results (>=2.4.2,<3.0.0)
Requires-Dist: langchain
Requires-Dist: llama-cpp-python[server] (>=0.1.57,<0.2.0)
Requires-Dist: openai (>=0.27,<0.28)
Requires-Dist: python-dotenv (>=1.0.0,<2.0.0)
Requires-Dist: termcolor (>=2.3.0,<3.0.0)
